COPYING
GPL-3
MANIFEST
MANIFEST.in
README.txt
setup.py
bin/diamond
diamond/TextBufferMarkup.py
diamond/__init__.py
diamond/attributewidget.py
diamond/choice.py
diamond/commentwidget.py
diamond/config.py
diamond/databuttonswidget.py
diamond/datatype.py
diamond/datawidget.py
diamond/debug.py
diamond/descriptionwidget.py
diamond/dialogs.py
diamond/diffview.py
diamond/interface.py
diamond/mixedtree.py
diamond/plist.py
diamond/plugins.py
diamond/preprocess.py
diamond/pygtkconsole.py
diamond/schema.py
diamond/schemausage.py
diamond/scherror.py
diamond/sliceview.py
diamond/tree.py
diamond/triangle_reader.py
diamond/useview.py
gui/diamond.svg
gui/gui.glade
schema/spud_base.rnc
schema/spud_base.rng
spud_diamond.egg-info/PKG-INFO
spud_diamond.egg-info/SOURCES.txt
spud_diamond.egg-info/dependency_links.txt
spud_diamond.egg-info/top_level.txt