Metadata-Version: 2.1
Name: spud-diamond
Version: 1.3
Summary: Model option preprocessor
Home-page: http://candylab.org
Author: The ICOM team and collaborators
Author-email: contact@candylab.org
License: UNKNOWN
Platform: UNKNOWN
